hf_s3_mirror/__init__.py
hf_s3_mirror/cli.py
hf_s3_mirror/s3_client.py
hf_s3_mirror-0.4.1.dist-info/METADATA
hf_s3_mirror-0.4.1.dist-info/WHEEL
hf_s3_mirror-0.4.1.dist-info/entry_points.txt
hf_s3_mirror-0.4.1.dist-info/licenses/LICENSE
hf_s3_mirror-0.4.1.dist-info/RECORD
